LICENSE
MANIFEST.in
README.rst
pyproject.toml
docs/Makefile
docs/conf.py
docs/index.rst
geonames_postcode/__init__.py
geonames_postcode/fetch.ini
geonames_postcode/fetch.py
geonames_postcode.egg-info/PKG-INFO
geonames_postcode.egg-info/SOURCES.txt
geonames_postcode.egg-info/dependency_links.txt
geonames_postcode.egg-info/entry_points.txt
geonames_postcode.egg-info/requires.txt
geonames_postcode.egg-info/top_level.txt
geonames_postcode/data/__init__.py
geonames_postcode/data/template