Metadata-Version: 2.4
Name: geonames_postcode
Version: 0.3
Summary: geonames_postcode is a Python package to make geonames.org postcode databases accessible in Python. It provides a command line tool to fetch, preprocess, and store the data in a Python file per country. In the result very fast (in-memory) queries by postcodes and names are available using just a few MB per country. Some helper functions are part of the package to solve common tasks like getting distances and finding postcodes nearby.
Author-email: André Wobst <project.geonames_postcode@wobsta.de>
License-Expression: GPL-2.0-or-later
Project-URL: Homepage, https://github.com/wobsta/geonames_postcode
Project-URL: Documentation, https://geonames-postcode.readthedocs.io/
Project-URL: Repository, https://github.com/wobsta/geonames_postcode
Project-URL: Changelog, https://github.com/wobsta/geonames_postcode/blob/master/CHANGES
Project-URL: Issues, https://github.com/wobsta/geonames_postcode/issues
Classifier: Development Status :: 4 - Beta
Classifier: Intended Audience :: Developers
Classifier: Operating System :: OS Independent
Classifier: Programming Language :: Python :: 2.7
Classifier: Programming Language :: Python :: 3
License-File: LICENSE
Provides-Extra: dev
Requires-Dist: sphinx; extra == "dev"
Dynamic: license-file
